trappist/__init__.py
trappist/bnet.py
trappist/conj.py
trappist/cp.py
trappist/ilp.py
trappist/max_sat.py
trappist/naive.py
trappist/trappist.py
trappist-1.1.3.dist-info/METADATA
trappist-1.1.3.dist-info/WHEEL
trappist-1.1.3.dist-info/entry_points.txt
trappist-1.1.3.dist-info/licenses/LICENSE
trappist-1.1.3.dist-info/RECORD
