Metadata-Version: 2.3
Name: trappist
Version: 1.1.3
Summary: Minimal Trap Spaces computation using Maximal Siphons
Project-URL: Code, https://github.com/soli/trap-spaces-as-siphons
Author-email: Sylvain Soliman <Sylvain.Soliman@inria.fr>
License-Expression: GPL-3.0
License-File: LICENSE
Classifier: Development Status :: 4 - Beta
Classifier: License :: OSI Approved :: GNU General Public License v3 (GPLv3)
Classifier: Operating System :: OS Independent
Classifier: Programming Language :: Python :: 3
Requires-Python: >=3.6
Requires-Dist: loguru>=0.2.5
Requires-Dist: minizinc>=0.6
Requires-Dist: networkx>=2.2
Requires-Dist: pyeda>=0.28
Requires-Dist: python-sat>=1.8.dev1
Provides-Extra: dev
Requires-Dist: ruff>=0.3; extra == 'dev'
